{"stat.craftItem.mfm.obsidian_spade":1,"stat.mineBlock.minecraft.mossy_cobblestone":2,"stat.walkOneCm":2623,"achievement.openInventory":6,"stat.pickup.minecraft.stick":2,"stat.craftItem.mfm.obsidian_axe":1,"stat.useItem.mfm.obsidian_spade":1,"stat.leaveGame":1,"stat.damageTaken":35,"stat.useItem.mfm.obsidian_pickaxe":2,"stat.useItem.mfm.obsidian_axe":1,"stat.flyOneCm":442,"stat.jump":13,"stat.playOneMinute":1726,"stat.fallOneCm":209,"stat.useItem.mfm.obsidian_sword":1,"stat.craftItem.mfm.obsidian_pickaxe":1,"stat.damageDealt":99,"stat.timeSinceDeath":1726,"achievement.exploreAllBiomes":{"value":0,"progress":["Redwood Taiga Hills M","Taiga"]},"stat.pickup.mfm.obsidianingot":3,"stat.craftItem.mfm.obsidian_sword":1,"stat.pickup.minecraft.mossy_cobblestone":2,"stat.craftingTableInteraction":1}